async_drf/__init__.py
async_drf/mixins.py
async_drf/views.py
async_drf/viewsets.py
async_drf-0.0.3.dist-info/LICENSE
async_drf-0.0.3.dist-info/METADATA
async_drf-0.0.3.dist-info/WHEEL
async_drf-0.0.3.dist-info/top_level.txt
async_drf-0.0.3.dist-info/RECORD
