Metadata-Version: 2.1
Name: async-drf
Version: 0.0.3
Summary: Async views and viewsets for DRF
Author: Diyor Khaydarov
License: UNKNOWN
Platform: UNKNOWN
Classifier: Programming Language :: Python :: 3
Classifier: License :: OSI Approved :: MIT License
Classifier: Operating System :: OS Independent
Requires-Python: >=3.6
License-File: LICENSE
Requires-Dist: Django
Requires-Dist: djangorestframework
